exppandas/__init__.py
exppandas/core.py
exppandas/version.py
exppandas-0.1.2.dist-info/LICENSE
exppandas-0.1.2.dist-info/METADATA
exppandas-0.1.2.dist-info/WHEEL
exppandas-0.1.2.dist-info/top_level.txt
exppandas-0.1.2.dist-info/RECORD
