Metadata-Version: 2.1
Name: exppandas
Version: 0.1.2
Summary: Enhanced version of Pandas with improved data manipulation capabilities
Home-page: https://github.com/Sumedh1599/exppandas
Author: Sumedh Patil
Author-email: sumedh@aipresso.com
License: UNKNOWN
Project-URL: Bug Reports, https://github.com/Sumedh1599/exppandas/issues
Project-URL: Source, https://github.com/Sumedh1599/exppandas
Project-URL: Documentation, https://exppandas.readthedocs.io/
Platform: UNKNOWN
Classifier: Development Status :: 4 - Beta
Classifier: Intended Audience :: Developers
Classifier: License :: OSI Approved :: MIT License
Classifier: Programming Language :: Python :: 3
Classifier: Programming Language :: Python :: 3.7
Classifier: Programming Language :: Python :: 3.8
Classifier: Programming Language :: Python :: 3.9
Classifier: Programming Language :: Python :: 3.10
Requires-Python: >=3.7
License-File: LICENSE
Requires-Dist: pandas (>=1.0.0)
Requires-Dist: numpy (>=1.20.0)
Requires-Dist: scipy (>=1.7.0)
Provides-Extra: dev
Requires-Dist: pytest (>=7.0.0) ; extra == 'dev'
Requires-Dist: pytest-cov (>=4.0.0) ; extra == 'dev'
Requires-Dist: black (>=23.0.0) ; extra == 'dev'
Requires-Dist: isort (>=5.0.0) ; extra == 'dev'
Requires-Dist: sphinx (>=5.0.0) ; extra == 'dev'
Requires-Dist: sphinx-rtd-theme (>=1.0.0) ; extra == 'dev'
